rng_lib/__init__.py
rng_lib/main.py
py_rng_lib-0.0.1.dist-info/LICENSE
py_rng_lib-0.0.1.dist-info/METADATA
py_rng_lib-0.0.1.dist-info/WHEEL
py_rng_lib-0.0.1.dist-info/top_level.txt
py_rng_lib-0.0.1.dist-info/RECORD
